Metadata-Version: 1.0
Name: PS-TIFF-Reader1
Version: 0.5
Summary: TIFF FILE READER_
Home-page: UNKNOWN
Author: alex
Author-email: alex@parkafm.co.kr
License: UNKNOWN
Platform: UNKNOWN
